MANIFEST.in
setup.py
ava/__init__.py
ava/launcher.py
ava.egg-info/PKG-INFO
ava.egg-info/SOURCES.txt
ava.egg-info/dependency_links.txt
ava.egg-info/entry_points.txt
ava.egg-info/not-zip-safe
ava.egg-info/pbr.json
ava.egg-info/requires.txt
ava.egg-info/top_level.txt
ava/cmds/__init__.py
ava/cmds/agent.py
ava/cmds/cli.py
ava/cmds/info.py
ava/cmds/key.py
ava/cmds/pkg.py
ava/cmds/pod.py
ava/cmds/webapp.py
ava/core/__init__.py
ava/core/agent.py
ava/core/data.py
ava/core/extension.py
ava/core/mod_tasks.py
ava/core/mod_webhooks.py
ava/core/task.py
ava/core/webfront.py
ava/core/websocket.py
ava/runtime/__init__.py
ava/runtime/config.py
ava/runtime/environ.py
ava/runtime/package.py
ava/shell/__init__.py
ava/shell/base.py
ava/shell/console.py
ava/shell/factory.py
ava/shell/gtk.py
ava/shell/osx.py
ava/shell/win32.py
ava/spi/__init__.py
ava/spi/context.py
ava/spi/defines.py
ava/spi/errors.py
ava/spi/signals.py
ava/spi/stores.py
ava/spi/task.py
ava/spi/webfront.py
ava/util/__init__.py
ava/util/codecs.py
ava/util/compat.py
ava/util/crypto.py
ava/util/tests.py
ava/util/time_uuid.py
ava/util/token.py
ava/util/webutils.py
ava/util/yaml.py
pod/__init__.py
pod/conf/__init__.py
pod/conf/ava.crt
pod/conf/ava.key
pod/conf/ava.yml
pod/data/__init__.py
pod/logs/__init__.py
pod/mods/__init__.py
pod/mods/commands/__init__.py
pod/mods/tasks/__init__.py
pod/mods/webhooks/__init__.py
pod/mods/webhooks/agent.py
pod/mods/webhooks/webroot.py
pod/pkgs/__init__.py
pod/webroot/bg.jpg
pod/webroot/favicon.ico
pod/webroot/index.html
pod/webroot/style.css
res/__init__.py
tests/functional/__init__.py
tests/functional/test_rest_api.py
tests/integration/__init__.py
tests/integration/test_data_engine.py
tests/integration/test_lmdb.py
tests/integration/test_msgpack.py
tests/integration/test_runtime_config.py
tests/integration/test_runtime_environ.py
tests/integration/test_task_engine.py
tests/provisional/__init__.py
tests/provisional/test_websocket.py
tests/unit/__init__.py
tests/unit/test_crypto.py
tests/unit/test_shell.py
tests/unit/test_signals.py
tests/unit/test_supervisotr.py
tests/unit/test_util.py
tests/unit/test_yaml.py