Metadata-Version: 1.0
Name: ava
Version: 0.1.1427870901
Summary: EAvatar Ava - A versatile agent.
Home-page: http://www.eavatar.com
Author: Sam Kuo
Author-email: sam@eavatar.com
License: UNKNOWN
Platform: UNKNOWN
